blasttools/__init__.py
blasttools/__main__.py
blasttools/blastapi.py
blasttools/blastxml.py
blasttools/cli.py
blasttools/columns.py
blasttools/config.py
blasttools/exact.py
blasttools/options.py
blasttools/plants.py
blasttools/plants_ui.py
blasttools/py.typed
blasttools/translate.py
blasttools/utils.py
blasttools-0.1.16.dist-info/LICENSE
blasttools-0.1.16.dist-info/METADATA
blasttools-0.1.16.dist-info/WHEEL
blasttools-0.1.16.dist-info/entry_points.txt
blasttools-0.1.16.dist-info/RECORD
