Metadata-Version: 2.1
Name: blasttools
Version: 0.1.16
Summary: Commands for turning blast queries into pandas dataframes.
Home-page: https://github.com/arabidopsis/blasttools
License: MIT
Keywords: genomics,bioinformatics
Author: Ian Castleden
Author-email: ian.castleden@uwa.edu.au
Requires-Python: >=3.9,<3.13
Classifier: Development Status :: 4 - Beta
Classifier: Intended Audience :: Science/Research
Classifier: License :: OSI Approved :: MIT License
Classifier: Programming Language :: Python :: 3
Classifier: Programming Language :: Python :: 3.9
Classifier: Programming Language :: Python :: 3.10
Classifier: Programming Language :: Python :: 3.11
Classifier: Programming Language :: Python :: 3.12
Classifier: Programming Language :: Python :: 3 :: Only
Classifier: Topic :: Scientific/Engineering :: Bio-Informatics
Requires-Dist: biopython (>=1.81,<2.0)
Requires-Dist: click (>=8.1.7,<9.0.0)
Requires-Dist: pandas (>=2.1.1,<3.0.0)
Project-URL: Repository, https://github.com/arabidopsis/blasttools
